MANIFEST.in
README.md
setup.py
docs/gen_ref_pages.py
qudra/VERSION.txt
qudra/__init__.py
qudra.egg-info/PKG-INFO
qudra.egg-info/SOURCES.txt
qudra.egg-info/dependency_links.txt
qudra.egg-info/requires.txt
qudra.egg-info/top_level.txt
qudra/optimizers/__init__.py
qudra/optimizers/distributed_energy.py
site/gen_ref_pages.py