Metadata-Version: 2.1
Name: qudra
Version: 0.1.1
Summary: Quantum Energy Management
Home-page: https://github.com/Q-Energy-2022/NYUAD-2022
Author: Asil Qraini, Fouad Afiouni, Gargi Chandrakar, Nurgazy Seidaliev, Sahar Ben Rached, Salem Al Haddad, Sarthak Prasad Malla. Mentors: Akash Kant, Shantanu Jha.
Author-email: shantanu.rajesh.jha@gmail.com
License: MIT
Project-URL: Documentation, https://github.com/Q-Energy-2022/NYUAD-2022
Project-URL: Source Code, https://github.com/Q-Energy-2022/NYUAD-2022
Project-URL: Tutorials, https://github.com/Q-Energy-2022/NYUAD-2022/tree/main/tutorials
Keywords: qubo energy vqe quantum computing
Platform: UNKNOWN
Classifier: Environment :: Console
Classifier: License :: OSI Approved :: MIT License
Classifier: Intended Audience :: Developers
Classifier: Intended Audience :: Science/Research
Classifier: Operating System :: Microsoft :: Windows
Classifier: Operating System :: MacOS :: MacOS X
Classifier: Operating System :: POSIX :: Linux
Classifier: Programming Language :: Python :: 3 :: Only
Classifier: Topic :: Scientific/Engineering
Requires-Python: >=3.7
Provides-Extra: dev
